statscraper/BaseScraperList.py
statscraper/BaseScraperObject.py
statscraper/DimensionValue.py
statscraper/ValueList.py
statscraper/__init__.py
statscraper/base_scraper.py
statscraper/compat.py
statscraper/datatypes.py
statscraper/exceptions.py
statscraper/datatypes/LICENSE
statscraper/datatypes/README.md
statscraper/datatypes/datatypes.csv
statscraper/datatypes/values/currencies.csv
statscraper/datatypes/values/genders.csv
statscraper/datatypes/values/marital_statuses.csv
statscraper/datatypes/values/road_types.csv
statscraper/datatypes/values/periods/months.csv
statscraper/datatypes/values/periods/quarters.csv
statscraper/datatypes/values/periods/academic-terms/semesters.csv
statscraper/datatypes/values/regions/eu.csv
statscraper/datatypes/values/regions/sweden/counties.csv
statscraper/datatypes/values/regions/sweden/municipalities.csv
statscraper/scrapers/CranesScraper.py
statscraper/scrapers/PXWebScraper.py
statscraper/scrapers/SCBScraper.py
statscraper/scrapers/SMHIScraper.py
statscraper/scrapers/StatistikcentralenScraper.py
statscraper/scrapers/VantetiderScraper.py
statscraper/scrapers/VehicleScraper.py
statscraper/scrapers/__init__.py
statscraper/scrapers/uka_scraper.py
statscraper/scrapers/work_injury_scraper.py
statscraper-2.0.2.dist-info/LICENSE
statscraper-2.0.2.dist-info/METADATA
statscraper-2.0.2.dist-info/WHEEL
statscraper-2.0.2.dist-info/top_level.txt
statscraper-2.0.2.dist-info/RECORD
