Metadata-Version: 2.1
Name: statscraper
Version: 2.0.2
Summary: A base class for building web scrapers for statistical data.
Home-page: https://github.com/jplusplus/statscraper
Author: Jens Finnäs and Leo Wallentin, J++; Robin Linderborg
Author-email: stockholm@jplusplus.org
License: MIT
Download-URL: https://github.com/jplusplus/skrejperpark/archive/2.0.2.tar.gz
Platform: UNKNOWN
Requires-Python: >=3.6
License-File: LICENSE
Requires-Dist: pandas
Requires-Dist: requests
Requires-Dist: six
